package com.tencent.mm.plugin.appbrand.config;

import android.database.Cursor;
import com.tencent.gmtrace.GMTrace;
import com.tencent.mm.bt.g;
import com.tencent.mm.sdk.e.c;
import com.tencent.mm.sdk.platformtools.bg;
import com.tencent.mm.sdk.platformtools.w;
import com.tencent.mm.x.ab;
import java.util.Iterator;
import java.util.LinkedList;
import java.util.List;
import org.json.JSONArray;

public final class f
{
  public f()
  {
    GMTrace.i(15531272830976L, 115717);
    GMTrace.o(15531272830976L, 115717);
  }
  
  private static <T> JSONArray R(List<T> paramList)
  {
    GMTrace.i(15531675484160L, 115720);
    JSONArray localJSONArray = new JSONArray();
    if (!bg.bX(paramList))
    {
      paramList = paramList.iterator();
      while (paramList.hasNext()) {
        localJSONArray.put(paramList.next());
      }
    }
    GMTrace.o(15531675484160L, 115720);
    return localJSONArray;
  }
  
  /* Error */
  static WxaAttributes a(m paramm)
  {
    // Byte code:
    //   0: aconst_null
    //   1: astore_2
    //   2: ldc2_w 64
    //   5: ldc 66
    //   7: invokestatic 19	com/tencent/gmtrace/GMTrace:i	(JI)V
    //   10: new 68	com/tencent/mm/plugin/appbrand/config/WxaAttributes
    //   13: dup
    //   14: invokespecial 69	com/tencent/mm/plugin/appbrand/config/WxaAttributes:<init>	()V
    //   17: astore_3
    //   18: aload_3
    //   19: aload_0
    //   20: getfield 75	com/tencent/mm/plugin/appbrand/config/m:field_brandId	Ljava/lang/String;
    //   23: putfield 78	com/tencent/mm/plugin/appbrand/config/WxaAttributes:field_username	Ljava/lang/String;
    //   26: aload_3
    //   27: aload_0
    //   28: getfield 81	com/tencent/mm/plugin/appbrand/config/m:field_appId	Ljava/lang/String;
    //   31: putfield 82	com/tencent/mm/plugin/appbrand/config/WxaAttributes:field_appId	Ljava/lang/String;
    //   34: aload_3
    //   35: aload_0
    //   36: getfield 85	com/tencent/mm/plugin/appbrand/config/m:field_appName	Ljava/lang/String;
    //   39: putfield 88	com/tencent/mm/plugin/appbrand/config/WxaAttributes:field_nickname	Ljava/lang/String;
    //   42: aload_3
    //   43: aload_0
    //   44: getfield 91	com/tencent/mm/plugin/appbrand/config/m:field_appIcon	Ljava/lang/String;
    //   47: putfield 94	com/tencent/mm/plugin/appbrand/config/WxaAttributes:field_brandIconURL	Ljava/lang/String;
    //   50: aload_3
    //   51: aload_0
    //   52: getfield 97	com/tencent/mm/plugin/appbrand/config/m:field_roundedSquareIcon	Ljava/lang/String;
    //   55: putfield 100	com/tencent/mm/plugin/appbrand/config/WxaAttributes:field_roundedSquareIconURL	Ljava/lang/String;
    //   58: aload_3
    //   59: aload_0
    //   60: getfield 103	com/tencent/mm/plugin/appbrand/config/m:field_BigHeadImgUrl	Ljava/lang/String;
    //   63: putfield 106	com/tencent/mm/plugin/appbrand/config/WxaAttributes:field_bigHeadURL	Ljava/lang/String;
    //   66: aload_3
    //   67: aconst_null
    //   68: putfield 109	com/tencent/mm/plugin/appbrand/config/WxaAttributes:field_smallHeadURL	Ljava/lang/String;
    //   71: aload_3
    //   72: aload_0
    //   73: getfield 112	com/tencent/mm/plugin/appbrand/config/m:field_signature	Ljava/lang/String;
    //   76: putfield 113	com/tencent/mm/plugin/appbrand/config/WxaAttributes:field_signature	Ljava/lang/String;
    //   79: aload_3
    //   80: aload_0
    //   81: getfield 117	com/tencent/mm/plugin/appbrand/config/m:field_AppOpt	I
    //   84: putfield 120	com/tencent/mm/plugin/appbrand/config/WxaAttributes:field_appOpt	I
    //   87: new 122	org/json/JSONObject
    //   90: dup
    //   91: invokespecial 123	org/json/JSONObject:<init>	()V
    //   94: astore 4
    //   96: aload 4
    //   98: ldc 125
    //   100: aload_3
    //   101: getfield 82	com/tencent/mm/plugin/appbrand/config/WxaAttributes:field_appId	Ljava/lang/String;
    //   104: invokevirtual 129	org/json/JSONObject:putOpt	(Ljava/lang/String;Ljava/lang/Object;)Lorg/json/JSONObject;
    //   107: pop
    //   108: new 122	org/json/JSONObject
    //   111: dup
    //   112: invokespecial 123	org/json/JSONObject:<init>	()V
    //   115: astore_1
    //   116: aload_1
    //   117: ldc -125
    //   119: aload_0
    //   120: getfield 135	com/tencent/mm/plugin/appbrand/config/m:field_appInfo	Lcom/tencent/mm/protocal/c/bsm;
    //   123: getfield 141	com/tencent/mm/protocal/c/bsm:uHn	Lcom/tencent/mm/protocal/c/cw;
    //   126: getfield 147	com/tencent/mm/protocal/c/cw:two	J
    //   129: invokestatic 153	java/lang/Long:valueOf	(J)Ljava/lang/Long;
    //   132: invokevirtual 129	org/json/JSONObject:putOpt	(Ljava/lang/String;Ljava/lang/Object;)Lorg/json/JSONObject;
    //   135: pop
    //   136: aload_1
    //   137: ldc -101
    //   139: aload_0
    //   140: getfield 135	com/tencent/mm/plugin/appbrand/config/m:field_appInfo	Lcom/tencent/mm/protocal/c/bsm;
    //   143: getfield 141	com/tencent/mm/protocal/c/bsm:uHn	Lcom/tencent/mm/protocal/c/cw;
    //   146: getfield 158	com/tencent/mm/protocal/c/cw:twv	Ljava/lang/String;
    //   149: invokevirtual 129	org/json/JSONObject:putOpt	(Ljava/lang/String;Ljava/lang/Object;)Lorg/json/JSONObject;
    //   152: pop
    //   153: aload 4
    //   155: ldc -96
    //   157: aload_1
    //   158: invokevirtual 129	org/json/JSONObject:putOpt	(Ljava/lang/String;Ljava/lang/Object;)Lorg/json/JSONObject;
    //   161: pop
    //   162: new 122	org/json/JSONObject
    //   165: dup
    //   166: invokespecial 123	org/json/JSONObject:<init>	()V
    //   169: astore 5
    //   171: aload_0
    //   172: getfield 135	com/tencent/mm/plugin/appbrand/config/m:field_appInfo	Lcom/tencent/mm/protocal/c/bsm;
    //   175: getfield 164	com/tencent/mm/protocal/c/bsm:uHl	Lcom/tencent/mm/protocal/c/aoo;
    //   178: astore 6
    //   180: aload 6
    //   182: ifnonnull +555 -> 737
    //   185: aconst_null
    //   186: astore_1
    //   187: aload 5
    //   189: ldc -90
    //   191: aload_1
    //   192: invokestatic 168	com/tencent/mm/plugin/appbrand/config/f:R	(Ljava/util/List;)Lorg/json/JSONArray;
    //   195: invokevirtual 129	org/json/JSONObject:putOpt	(Ljava/lang/String;Ljava/lang/Object;)Lorg/json/JSONObject;
    //   198: pop
    //   199: aload 6
    //   201: ifnonnull +545 -> 746
    //   204: aconst_null
    //   205: astore_1
    //   206: aload 5
    //   208: ldc -86
    //   210: aload_1
    //   211: invokestatic 168	com/tencent/mm/plugin/appbrand/config/f:R	(Ljava/util/List;)Lorg/json/JSONArray;
    //   214: invokevirtual 129	org/json/JSONObject:putOpt	(Ljava/lang/String;Ljava/lang/Object;)Lorg/json/JSONObject;
    //   217: pop
    //   218: aload 6
    //   220: ifnonnull +535 -> 755
    //   223: aconst_null
    //   224: astore_1
    //   225: aload 5
    //   227: ldc -84
    //   229: aload_1
    //   230: invokestatic 168	com/tencent/mm/plugin/appbrand/config/f:R	(Ljava/util/List;)Lorg/json/JSONArray;
    //   233: invokevirtual 129	org/json/JSONObject:putOpt	(Ljava/lang/String;Ljava/lang/Object;)Lorg/json/JSONObject;
    //   236: pop
    //   237: aload 6
    //   239: ifnonnull +525 -> 764
    //   242: aload_2
    //   243: astore_1
    //   244: aload 5
    //   246: ldc -82
    //   248: aload_1
    //   249: invokestatic 168	com/tencent/mm/plugin/appbrand/config/f:R	(Ljava/util/List;)Lorg/json/JSONArray;
    //   252: invokevirtual 129	org/json/JSONObject:putOpt	(Ljava/lang/String;Ljava/lang/Object;)Lorg/json/JSONObject;
    //   255: pop
    //   256: aload 4
    //   258: ldc -80
    //   260: aload 5
    //   262: invokevirtual 129	org/json/JSONObject:putOpt	(Ljava/lang/String;Ljava/lang/Object;)Lorg/json/JSONObject;
    //   265: pop
    //   266: aload_3
    //   267: aload 4
    //   269: invokevirtual 180	org/json/JSONObject:toString	()Ljava/lang/String;
    //   272: putfield 182	com/tencent/mm/plugin/appbrand/config/WxaAttributes:field_appInfo	Ljava/lang/String;
    //   275: new 122	org/json/JSONObject
    //   278: dup
    //   279: invokespecial 123	org/json/JSONObject:<init>	()V
    //   282: astore_1
    //   283: aload_0
    //   284: getfield 135	com/tencent/mm/plugin/appbrand/config/m:field_appInfo	Lcom/tencent/mm/protocal/c/bsm;
    //   287: ifnull +173 -> 460
    //   290: aload_0
    //   291: getfield 135	com/tencent/mm/plugin/appbrand/config/m:field_appInfo	Lcom/tencent/mm/protocal/c/bsm;
    //   294: getfield 186	com/tencent/mm/protocal/c/bsm:uHk	Lcom/tencent/mm/protocal/c/cx;
    //   297: ifnull +163 -> 460
    //   300: new 122	org/json/JSONObject
    //   303: dup
    //   304: invokespecial 123	org/json/JSONObject:<init>	()V
    //   307: astore_2
    //   308: aload_0
    //   309: getfield 135	com/tencent/mm/plugin/appbrand/config/m:field_appInfo	Lcom/tencent/mm/protocal/c/bsm;
    //   312: getfield 186	com/tencent/mm/protocal/c/bsm:uHk	Lcom/tencent/mm/protocal/c/cx;
    //   315: astore 4
    //   317: aload_2
    //   318: ldc -68
    //   320: aload 4
    //   322: getfield 193	com/tencent/mm/protocal/c/cx:tww	I
    //   325: invokestatic 198	java/lang/Integer:valueOf	(I)Ljava/lang/Integer;
    //   328: invokevirtual 129	org/json/JSONObject:putOpt	(Ljava/lang/String;Ljava/lang/Object;)Lorg/json/JSONObject;
    //   331: pop
    //   332: aload_2
    //   333: ldc -56
    //   335: aload 4
    //   337: getfield 203	com/tencent/mm/protocal/c/cx:twx	I
    //   340: invokestatic 198	java/lang/Integer:valueOf	(I)Ljava/lang/Integer;
    //   343: invokevirtual 129	org/json/JSONObject:putOpt	(Ljava/lang/String;Ljava/lang/Object;)Lorg/json/JSONObject;
    //   346: pop
    //   347: aload_2
    //   348: ldc -51
    //   350: aload 4
    //   352: getfield 208	com/tencent/mm/protocal/c/cx:twy	I
    //   355: invokestatic 198	java/lang/Integer:valueOf	(I)Ljava/lang/Integer;
    //   358: invokevirtual 129	org/json/JSONObject:putOpt	(Ljava/lang/String;Ljava/lang/Object;)Lorg/json/JSONObject;
    //   361: pop
    //   362: aload_2
    //   363: ldc -46
    //   365: aload 4
    //   367: getfield 213	com/tencent/mm/protocal/c/cx:twz	I
    //   370: invokestatic 198	java/lang/Integer:valueOf	(I)Ljava/lang/Integer;
    //   373: invokevirtual 129	org/json/JSONObject:putOpt	(Ljava/lang/String;Ljava/lang/Object;)Lorg/json/JSONObject;
    //   376: pop
    //   377: aload_2
    //   378: ldc -41
    //   380: aload 4
    //   382: getfield 218	com/tencent/mm/protocal/c/cx:twA	I
    //   385: invokestatic 198	java/lang/Integer:valueOf	(I)Ljava/lang/Integer;
    //   388: invokevirtual 129	org/json/JSONObject:putOpt	(Ljava/lang/String;Ljava/lang/Object;)Lorg/json/JSONObject;
    //   391: pop
    //   392: aload_2
    //   393: ldc -36
    //   395: aload 4
    //   397: getfield 223	com/tencent/mm/protocal/c/cx:twB	I
    //   400: invokestatic 198	java/lang/Integer:valueOf	(I)Ljava/lang/Integer;
    //   403: invokevirtual 129	org/json/JSONObject:putOpt	(Ljava/lang/String;Ljava/lang/Object;)Lorg/json/JSONObject;
    //   406: pop
    //   407: aload_2
    //   408: ldc -31
    //   410: aload 4
    //   412: getfield 228	com/tencent/mm/protocal/c/cx:twC	I
    //   415: invokestatic 198	java/lang/Integer:valueOf	(I)Ljava/lang/Integer;
    //   418: invokevirtual 129	org/json/JSONObject:putOpt	(Ljava/lang/String;Ljava/lang/Object;)Lorg/json/JSONObject;
    //   421: pop
    //   422: aload_2
    //   423: ldc -26
    //   425: aload 4
    //   427: getfield 233	com/tencent/mm/protocal/c/cx:twD	I
    //   430: invokestatic 198	java/lang/Integer:valueOf	(I)Ljava/lang/Integer;
    //   433: invokevirtual 129	org/json/JSONObject:putOpt	(Ljava/lang/String;Ljava/lang/Object;)Lorg/json/JSONObject;
    //   436: pop
    //   437: aload_2
    //   438: ldc -21
    //   440: aload 4
    //   442: getfield 238	com/tencent/mm/protocal/c/cx:iIQ	I
    //   445: invokestatic 198	java/lang/Integer:valueOf	(I)Ljava/lang/Integer;
    //   448: invokevirtual 129	org/json/JSONObject:putOpt	(Ljava/lang/String;Ljava/lang/Object;)Lorg/json/JSONObject;
    //   451: pop
    //   452: aload_1
    //   453: ldc -16
    //   455: aload_2
    //   456: invokevirtual 129	org/json/JSONObject:putOpt	(Ljava/lang/String;Ljava/lang/Object;)Lorg/json/JSONObject;
    //   459: pop
    //   460: aload_0
    //   461: getfield 244	com/tencent/mm/plugin/appbrand/config/m:field_versionInfo	Lcom/tencent/mm/protocal/c/bss;
    //   464: ifnull +103 -> 567
    //   467: aload_0
    //   468: getfield 244	com/tencent/mm/plugin/appbrand/config/m:field_versionInfo	Lcom/tencent/mm/protocal/c/bss;
    //   471: getfield 250	com/tencent/mm/protocal/c/bss:tKz	Ljava/util/LinkedList;
    //   474: ifnull +93 -> 567
    //   477: new 30	org/json/JSONArray
    //   480: dup
    //   481: invokespecial 31	org/json/JSONArray:<init>	()V
    //   484: astore_2
    //   485: aload_0
    //   486: getfield 244	com/tencent/mm/plugin/appbrand/config/m:field_versionInfo	Lcom/tencent/mm/protocal/c/bss;
    //   489: getfield 250	com/tencent/mm/protocal/c/bss:tKz	Ljava/util/LinkedList;
    //   492: invokevirtual 253	java/util/LinkedList:iterator	()Ljava/util/Iterator;
    //   495: astore 4
    //   497: aload 4
    //   499: invokeinterface 49 1 0
    //   504: ifeq +269 -> 773
    //   507: aload 4
    //   509: invokeinterface 53 1 0
    //   514: checkcast 255	com/tencent/mm/protocal/c/jq
    //   517: astore 5
    //   519: new 122	org/json/JSONObject
    //   522: dup
    //   523: invokespecial 123	org/json/JSONObject:<init>	()V
    //   526: astore 6
    //   528: aload 6
    //   530: ldc_w 257
    //   533: aload 5
    //   535: getfield 260	com/tencent/mm/protocal/c/jq:tFI	Ljava/lang/String;
    //   538: invokevirtual 129	org/json/JSONObject:putOpt	(Ljava/lang/String;Ljava/lang/Object;)Lorg/json/JSONObject;
    //   541: pop
    //   542: aload 6
    //   544: ldc_w 262
    //   547: aload 5
    //   549: getfield 265	com/tencent/mm/protocal/c/jq:tFJ	Ljava/lang/String;
    //   552: invokevirtual 129	org/json/JSONObject:putOpt	(Ljava/lang/String;Ljava/lang/Object;)Lorg/json/JSONObject;
    //   555: pop
    //   556: aload_2
    //   557: aload 6
    //   559: invokevirtual 57	org/json/JSONArray:put	(Ljava/lang/Object;)Lorg/json/JSONArray;
    //   562: pop
    //   563: goto -66 -> 497
    //   566: astore_2
    //   567: aload_3
    //   568: aload_1
    //   569: invokevirtual 180	org/json/JSONObject:toString	()Ljava/lang/String;
    //   572: putfield 268	com/tencent/mm/plugin/appbrand/config/WxaAttributes:field_dynamicInfo	Ljava/lang/String;
    //   575: aload_0
    //   576: getfield 272	com/tencent/mm/plugin/appbrand/config/m:field_bindInfo	Lcom/tencent/mm/protocal/c/gm;
    //   579: ifnull +136 -> 715
    //   582: aload_0
    //   583: getfield 272	com/tencent/mm/plugin/appbrand/config/m:field_bindInfo	Lcom/tencent/mm/protocal/c/gm;
    //   586: getfield 277	com/tencent/mm/protocal/c/gm:tAF	Ljava/util/LinkedList;
    //   589: ifnull +126 -> 715
    //   592: new 122	org/json/JSONObject
    //   595: dup
    //   596: invokespecial 123	org/json/JSONObject:<init>	()V
    //   599: astore_1
    //   600: new 30	org/json/JSONArray
    //   603: dup
    //   604: invokespecial 31	org/json/JSONArray:<init>	()V
    //   607: astore_2
    //   608: aload_0
    //   609: getfield 272	com/tencent/mm/plugin/appbrand/config/m:field_bindInfo	Lcom/tencent/mm/protocal/c/gm;
    //   612: getfield 277	com/tencent/mm/protocal/c/gm:tAF	Ljava/util/LinkedList;
    //   615: invokevirtual 253	java/util/LinkedList:iterator	()Ljava/util/Iterator;
    //   618: astore_0
    //   619: aload_0
    //   620: invokeinterface 49 1 0
    //   625: ifeq +160 -> 785
    //   628: aload_0
    //   629: invokeinterface 53 1 0
    //   634: checkcast 279	com/tencent/mm/protocal/c/bsz
    //   637: astore 4
    //   639: new 122	org/json/JSONObject
    //   642: dup
    //   643: invokespecial 123	org/json/JSONObject:<init>	()V
    //   646: astore 5
    //   648: aload 5
    //   650: ldc_w 281
    //   653: aload 4
    //   655: getfield 283	com/tencent/mm/protocal/c/bsz:username	Ljava/lang/String;
    //   658: invokevirtual 129	org/json/JSONObject:putOpt	(Ljava/lang/String;Ljava/lang/Object;)Lorg/json/JSONObject;
    //   661: pop
    //   662: aload 5
    //   664: ldc_w 285
    //   667: aload 4
    //   669: getfield 288	com/tencent/mm/protocal/c/bsz:oqo	Ljava/lang/String;
    //   672: invokevirtual 129	org/json/JSONObject:putOpt	(Ljava/lang/String;Ljava/lang/Object;)Lorg/json/JSONObject;
    //   675: pop
    //   676: aload 5
    //   678: ldc_w 290
    //   681: aload 4
    //   683: getfield 292	com/tencent/mm/protocal/c/bsz:title	Ljava/lang/String;
    //   686: invokevirtual 129	org/json/JSONObject:putOpt	(Ljava/lang/String;Ljava/lang/Object;)Lorg/json/JSONObject;
    //   689: pop
    //   690: aload 5
    //   692: ldc_w 294
    //   695: aload 4
    //   697: getfield 297	com/tencent/mm/protocal/c/bsz:hoh	Ljava/lang/String;
    //   700: invokevirtual 129	org/json/JSONObject:putOpt	(Ljava/lang/String;Ljava/lang/Object;)Lorg/json/JSONObject;
    //   703: pop
    //   704: aload_2
    //   705: aload 5
    //   707: invokevirtual 57	org/json/JSONArray:put	(Ljava/lang/Object;)Lorg/json/JSONArray;
    //   710: pop
    //   711: goto -92 -> 619
    //   714: astore_0
    //   715: aload_3
    //   716: lconst_0
    //   717: putfield 300	com/tencent/mm/plugin/appbrand/config/WxaAttributes:field_syncTimeSecond	J
    //   720: aload_3
    //   721: ldc_w 302
    //   724: putfield 305	com/tencent/mm/plugin/appbrand/config/WxaAttributes:field_syncVersion	Ljava/lang/String;
    //   727: ldc2_w 64
    //   730: ldc 66
    //   732: invokestatic 22	com/tencent/gmtrace/GMTrace:o	(JI)V
    //   735: aload_3
    //   736: areturn
    //   737: aload 6
    //   739: getfield 310	com/tencent/mm/protocal/c/aoo:ukG	Ljava/util/LinkedList;
    //   742: astore_1
    //   743: goto -556 -> 187
    //   746: aload 6
    //   748: getfield 313	com/tencent/mm/protocal/c/aoo:ukH	Ljava/util/LinkedList;
    //   751: astore_1
    //   752: goto -546 -> 206
    //   755: aload 6
    //   757: getfield 316	com/tencent/mm/protocal/c/aoo:ukI	Ljava/util/LinkedList;
    //   760: astore_1
    //   761: goto -536 -> 225
    //   764: aload 6
    //   766: getfield 319	com/tencent/mm/protocal/c/aoo:ukJ	Ljava/util/LinkedList;
    //   769: astore_1
    //   770: goto -526 -> 244
    //   773: aload_1
    //   774: ldc_w 321
    //   777: aload_2
    //   778: invokevirtual 129	org/json/JSONObject:putOpt	(Ljava/lang/String;Ljava/lang/Object;)Lorg/json/JSONObject;
    //   781: pop
    //   782: goto -215 -> 567
    //   785: aload_1
    //   786: ldc_w 323
    //   789: aload_2
    //   790: invokevirtual 129	org/json/JSONObject:putOpt	(Ljava/lang/String;Ljava/lang/Object;)Lorg/json/JSONObject;
    //   793: pop
    //   794: aload_3
    //   795: aload_1
    //   796: invokevirtual 180	org/json/JSONObject:toString	()Ljava/lang/String;
    //   799: putfield 326	com/tencent/mm/plugin/appbrand/config/WxaAttributes:field_bindWxaInfo	Ljava/lang/String;
    //   802: goto -87 -> 715
    //   805: astore_1
    //   806: goto -231 -> 575
    //   809: astore_2
    //   810: goto -350 -> 460
    //   813: astore_1
    //   814: goto -539 -> 275
    //   817: astore_1
    //   818: goto -552 -> 266
    //   821: astore_1
    //   822: goto -660 -> 162
    // Local variable table:
    //   start	length	slot	name	signature
    //   0	825	0	paramm	m
    //   115	681	1	localObject1	Object
    //   805	1	1	localException1	Exception
    //   813	1	1	localException2	Exception
    //   817	1	1	localException3	Exception
    //   821	1	1	localException4	Exception
    //   1	556	2	localObject2	Object
    //   566	1	2	localException5	Exception
    //   607	183	2	localJSONArray	JSONArray
    //   809	1	2	localException6	Exception
    //   17	778	3	localWxaAttributes	WxaAttributes
    //   94	602	4	localObject3	Object
    //   169	537	5	localObject4	Object
    //   178	587	6	localObject5	Object
    // Exception table:
    //   from	to	target	type
    //   460	497	566	java/lang/Exception
    //   497	563	566	java/lang/Exception
    //   773	782	566	java/lang/Exception
    //   575	619	714	java/lang/Exception
    //   619	711	714	java/lang/Exception
    //   785	802	714	java/lang/Exception
    //   275	283	805	java/lang/Exception
    //   567	575	805	java/lang/Exception
    //   283	460	809	java/lang/Exception
    //   87	108	813	java/lang/Exception
    //   266	275	813	java/lang/Exception
    //   162	180	817	java/lang/Exception
    //   187	199	817	java/lang/Exception
    //   206	218	817	java/lang/Exception
    //   225	237	817	java/lang/Exception
    //   244	266	817	java/lang/Exception
    //   737	743	817	java/lang/Exception
    //   746	752	817	java/lang/Exception
    //   755	761	817	java/lang/Exception
    //   764	770	817	java/lang/Exception
    //   108	162	821	java/lang/Exception
  }
}


/* Location:              /Users/xianghongyan/decompile/dex2jar/classes2-dex2jar.jar!/com/tencent/mm/plugin/appbrand/config/f.class
 * Java compiler version: 6 (50.0)
 * JD-Core Version:       0.7.1
 */